solving_auth_middleware/README.md
solving_auth_middleware/__init__.py
solving_auth_middleware/config.py
solving_auth_middleware/enums.py
solving_auth_middleware/middleware.py
solving_auth_middleware/middleware_v2.py
solving_auth_middleware/middleware_v3.py
solving_auth_middleware/validators.py
solving_auth_middleware-0.3.2.dist-info/METADATA
solving_auth_middleware-0.3.2.dist-info/WHEEL
solving_auth_middleware-0.3.2.dist-info/licenses/LICENSE
solving_auth_middleware-0.3.2.dist-info/RECORD
