Metadata-Version: 2.4
Name: solving-auth-middleware
Version: 0.3.2
Summary: Reusable middleware for jwt checking with modular validators and role hierarchy
License: MIT
License-File: LICENSE
Author: Sahmok
Author-email: mokrane@solving-company.fr
Requires-Python: >=3.10,<4
Classifier: License :: OSI Approved :: MIT License
Classifier: Programming Language :: Python :: 3
Classifier: Programming Language :: Python :: 3.10
Classifier: Programming Language :: Python :: 3.11
Classifier: Programming Language :: Python :: 3.12
Classifier: Programming Language :: Python :: 3.13
Classifier: Programming Language :: Python :: 3.14
Requires-Dist: flask (>=3.1.0,<4.0.0)
Requires-Dist: flask-jwt-extended (>=4.7.1,<5.0.0)
Requires-Dist: flask-restx (>=1.3.0,<2.0.0)
Requires-Dist: python-dotenv (>=1.0.0,<2.0.0)
